bancor_simulation/__init__.py
bancor_simulation/core.py
bancor_simulation-20.0.dist-info/METADATA
bancor_simulation-20.0.dist-info/WHEEL
bancor_simulation-20.0.dist-info/top_level.txt
bancor_simulation-20.0.dist-info/RECORD
